Workbook

Sheet Cost Projection
A1: Part A · Campus Threads Co.: projecting hoodie costs
A2: Campus Threads Co. sells hoodies to college students for $60. Should it switch from cotton to recycled fabric? Project what one hoodie costs to make for the next five years. Build every yellow cell with your own formulas (no AI in Parts A and B).
A3: Color key | B3: Input (given) | C3: You fill this
A5: Inputs
A6: Requirements per hoodie | B6: Cotton | C6: Recycled
A7: Fabric required (yards) | B7: 2 | C7: 1.8
A8: Labor hours required | B8: 0.5 | C8: 0.45
A10: Cost of fabric | B10: Cotton | C10: Recycled
A11: Current cost per yard | B11: 6 | C11: 7.75
A12: Projected annual increase | B12: 0.045 | C12: 0.01
A14: Cost of labor
A15: Current cost per labor hour | B15: 16
A16: Projected annual increase | B16: 0.035
A18: Other cost
A19: Printing & trim per hoodie (stays constant) | B19: 5
A21: Outputs: projected costs
B22: Cost per yard | D22: Cost per hour | E22: Cost per hoodie | G22: Recycled premium
A23: Years from now | B23: Cotton | C23: Recycled | D23: Labor | E23: Cotton | F23: Recycled | G23: (Recycled − Cotton)
A24: 0 | B24: =B$11*(1+B$12)^$A24 | C24: =C$11*(1+C$12)^$A24 | D24: =$B$15*(1+$B$16)^$A24 | E24: =B$7*B24+B$8*$D24+$B$19 | F24: =C$7*C24+C$8*$D24+$B$19 | G24: =F24-E24
A25: 1 | B25: =B$11*(1+B$12)^$A25 | C25: =C$11*(1+C$12)^$A25 | D25: =$B$15*(1+$B$16)^$A25 | E25: =B$7*B25+B$8*$D25+$B$19 | F25: =C$7*C25+C$8*$D25+$B$19 | G25: =F25-E25
A26: 2 | B26: =B$11*(1+B$12)^$A26 | C26: =C$11*(1+C$12)^$A26 | D26: =$B$15*(1+$B$16)^$A26 | E26: =B$7*B26+B$8*$D26+$B$19 | F26: =C$7*C26+C$8*$D26+$B$19 | G26: =F26-E26
A27: 3 | B27: =B$11*(1+B$12)^$A27 | C27: =C$11*(1+C$12)^$A27 | D27: =$B$15*(1+$B$16)^$A27 | E27: =B$7*B27+B$8*$D27+$B$19 | F27: =C$7*C27+C$8*$D27+$B$19 | G27: =F27-E27
A28: 4 | B28: =B$11*(1+B$12)^$A28 | C28: =C$11*(1+C$12)^$A28 | D28: =$B$15*(1+$B$16)^$A28 | E28: =B$7*B28+B$8*$D28+$B$19 | F28: =C$7*C28+C$8*$D28+$B$19 | G28: =F28-E28
A29: 5 | B29: =B$11*(1+B$12)^$A29 | C29: =C$11*(1+C$12)^$A29 | D29: =$B$15*(1+$B$16)^$A29 | E29: =B$7*B29+B$8*$D29+$B$19 | F29: =C$7*C29+C$8*$D29+$B$19 | G29: =F29-E29
A31: What-if: wages grow 6.0% a year instead of 3.5% (cell B16). What does one Cotton hoodie cost in year 5? | E31: 30.66
A32: Type the number in E31 (do not link it), then set B16 back to 3.5%.
A34: Steps (Part A)
A35: 1. In B24, write the Cotton cost per yard for year 0: cost today x (1 + annual increase) ^ years. Use $ signs so it copies right to C24 and down to row 29 (same pattern as B19 in the Bookshelf case). Copy it to B24:C29. Check: B24 = $6.00, C24 = $7.75, B25 = $6.27
A36: 2. In D24, write the Labor cost per hour and copy it down to D29. Labor has one rate for both hoodies, so lock both the column and the row of its inputs. Check: D24 = $16.00, D25 = $16.56
A37: 3. In E24, write the cost of one Cotton hoodie: fabric yards x cost per yard + labor hours x cost per hour + printing & trim. Write it so it copies right to F24 and down to row 29, then copy it to E24:F29. Check: E24 = $25.00, F24 = $26.15, E25 = $25.82
A38: 4. In G24, write Recycled premium = Recycled cost minus Cotton cost and copy it down to G29. A negative value means Recycled is cheaper. Check: G24 = $1.15
A39: 5. Chart: select A23:A29, hold Ctrl (Cmd on a Mac), select E23:F29, then Insert > Scatter > Scatter with Straight Lines and Markers. Add a chart title and both axis titles. Place it to the right of the table, near cell I5. Check: two lines that cross
A40: 6. Audit: Formulas > Show Formulas. Every cell in B24:G29 must show a formula, never a typed number. Click Show Formulas again to switch back.
A41: 7. Answer the what-if in row 31.

Sheet Break-even
A1: Part B · Campus Threads Co.: Instagram ad campaign break-even
A2: The owner plans to buy Instagram clicks to sell hoodies online. Will the campaign make money, and how easily could the profit disappear? Build every yellow cell with your own formulas. Blue = given input. Red = the decision (how many clicks to buy).
A3: Color key | B3: Input (given) | E3: Decision | G3: You fill this
A5: Campaign inputs | D5: Model of orders | G5: Table 1: profit vs number of clicks (one-way data table)
A6: Fixed cost of campaign (photo shoot, design) | B6: 6300 | D6: Conversion rate (share of clicks that become orders) | E6: 0.04 | G6: Clicks purchased | H6: Profit
A7: Cost per click | B7: 0.7 | D7: Number of orders | E7: =B10*E6 | H7: =E15
G8: 5000 | H8: -4200
A9: Decision variable | D9: Outputs: revenue, costs, and profit | G9: 10000 | H9: -2100
A10: Number of clicks purchased | B10: 25000 | D10: Total revenue | E10: =E7*B13 | G10: 15000 | H10: 0
D11: Fixed cost of campaign | E11: =B6 | G11: 20000 | H11: 2100
A12: Order inputs | D12: Total cost of clicks | E12: =B7*B10 | G12: 25000 | H12: 4200
A13: Average order | B13: 60 | D13: Total variable cost of orders | E13: =B14*E7 | G13: 30000 | H13: 6300
A14: Variable cost per order (hoodie + shipping + fees) | B14: 32 | D14: Total cost | E14: =SUM(E11:E13) | G14: 35000 | H14: 8400
D15: Profit | E15: =E10-E14 | G15: 40000 | H15: 10500
D17: Outputs: break-even analysis
D18: Margin per order | E18: =B13-B14 | G18: Table 2: profit for conversion rate (down) × clicks (across), two-way data table
D19: Contribution per click | E19: =E6*E18-B7 | G19: =E15 | H19: 10000 | I19: 15000 | J19: 25000 | K19: 40000 | L19: 60000
D20: Break-even number of clicks | E20: =B6/E19 | G20: 0.02 | H20: -7700 | I20: -8400 | J20: -9800 | K20: -11900 | L20: -14700
D21: Break-even conversion rate | E21: =(B6+E12)/(B10*E18) | G21: 0.03 | H21: -4900 | I21: -4200 | J21: -2800 | K21: -700 | L21: 2100
D22: Break-even average order | E22: =B14+(B6+E12)/E7 | G22: 0.04 | H22: -2100 | I22: 0 | J22: 4200 | K22: 10500 | L22: 18900
G23: 0.05 | H23: 700 | I23: 4200 | J23: 11200 | K23: 21700 | L23: 35700
G24: 0.06 | H24: 3500 | I24: 8400 | J24: 18200 | K24: 32900 | L24: 52500
A25: What-if: cost per click rises to $0.90 (cell B7). What is the profit? | B25: -800
A26: Type the number in B25 (do not link it), then set B7 back to $0.70.
A28: Steps (Part B)
A29: 1. In E7, write Number of orders = number of clicks x conversion rate.
A30: 2. Fill E10 to E15. Total revenue = orders x average order. Fixed cost = a link to B6. Total cost of clicks = cost per click x clicks. Total variable cost of orders = variable cost per order x orders. Total cost = the sum of the three costs. Profit = revenue minus total cost. Check: E10 = $60,000, E12 = $17,500
A31: 3. Fill the break-even block E18 to E22. Margin per order = average order minus variable cost per order. Contribution per click = conversion rate x margin per order minus cost per click. Break-even clicks = fixed cost / contribution per click. Break-even conversion rate = (fixed cost + total cost of clicks) / (clicks x margin per order). Break-even average order = variable cost per order + (fixed cost + total cost of clicks) / orders. Check: E18 = $28.00, E19 = $0.42
A32: 4. Confirm break-even clicks with Goal Seek: Data > What-If Analysis > Goal Seek. Set cell E15, To value 0, By changing cell B10. B10 should now equal E20. Then type 25000 back into B10. Check: B10 = 25,000 again
A33: 5. Table 1: in H7 type =E15. Select G7:H15, then Data > What-If Analysis > Data Table. Leave Row input cell empty; Column input cell: B10. Check: the 10,000 row shows -$2,100, and the 25,000 row equals E15
A34: 6. Table 2: in G19 type =E15. Select G19:L24, then Data Table. Row input cell: B10 (clicks run across the top). Column input cell: E6 (conversion rates run down the side). Check: 5% and 10,000 shows $700, and 4% and 25,000 equals E15
A35: 7. Answer the what-if in row 25. Before you move on, confirm B7 = $0.70, B10 = 25,000, B13 = $60.00 and E6 = 4.0%.

Sheet AI Report Log
A1: Part C · AI leadership report (RT-OC-QC prompt, verification, reflection)
A2: Fill every yellow box. Your AI tool writes the report on a new sheet named Leadership Summary. When you finish, save this one workbook and upload it in Canvas.
A3: Before you start, save a backup copy of this file. Use Claude in Excel as shown in class. If you cannot open it, attach this workbook to Microsoft Copilot Chat (USF sign-in), paste the same prompt, then paste its report into a new sheet named Leadership Summary and copy your Part A chart onto it. The Leadership Summary must have: a 2 to 4 bullet bottom line, a small table of key numbers, at least one chart, and 2 or 3 recommended actions. Afterwards, check that the AI did not change your model (Cost Projection E24 still $25.00, Break-even B10 still 25,000).
A4: 1. Tool
B5: Claude (Anthropic) via Claude Code - not Claude in Excel / Copilot | D5: Claude Sonnet 5.5
B6: Date I ran the prompt | D6: 2026-10-13
A8: 2. Build your RT-OC-QC prompt: one or two sentences in each yellow box, written for THIS case
B9: Part | C9: What it answers, with a tip | D9: Your wording for this case
A10: R | B10: Role | C10: Who should the AI act as? Example from class: "You are a business analyst." | D10: You are a business analyst advising the owner of Campus Threads Co., a small apparel company that sells hoodies to college students, who has no finance background.
A11: T | B11: Task | C11: What exactly should it do? Name the job in one sentence. | D11: Read my Cost Projection and Break-even sheets and write a leadership summary that answers two questions: (1) should we switch from cotton to recycled fabric, and (2) will the planned Instagram ad campaign make money and how easily could the profit disappear?
A12: O | B12: Output | C12: What should come back, for whom, in what format, and where? Audience, length, sections, visuals, and the sheet name 'Leadership Summary'. | D12: A new sheet named "Leadership Summary" for the owner, readable in two minutes: a 2-4 bullet bottom line, a small table of key numbers, at least one chart (cost per hoodie, cotton vs recycled, years 0-5), and 2-3 recommended actions, in plain English with $ and % formatting.
A13: C | B13: Context | C13: What does it need to know about this business and this workbook? Company, the two analyses, which sheets hold them, the decision leaders face. | D13: Hoodies sell for $60. Cost Projection (rows 24-29) projects cotton vs recycled cost per hoodie for 5 years (cotton fabric +4.5%/yr, recycled +1%/yr, labor +3.5%/yr). Break-even models a 25,000-click Instagram campaign: $6,300 fixed cost, $0.70/click, 4% conversion, $60 average order, $32 variable cost per order. Decisions: which fabric, and whether/how much to spend on ads.
A14: QC | B14: Quality Control | C14: What rules keep the result honest? Use only numbers from this workbook, show where each number came from, flag assumptions. | D14: Use only numbers that appear in this workbook and cite the sheet and cell for each. Do not change any cell in my existing sheets. Label every assumption (constant conversion rate, constant $5 printing, linear click-to-order model) and state limits of the model rather than guessing. If a number is not in the workbook, say so.
A16: 3. The full prompt exactly as I sent it (copy and paste)
B17: ROLE: You are a business analyst advising the owner of Campus Threads Co., a small apparel company that sells hoodies to college students, who has no finance background. TASK: Read my Cost Projection and Break-even sheets and write a leadership summary that answers two questions: (1) should we switch from cotton to recycled fabric, and (2) will the planned Instagram ad campaign make money and how easily could the profit disappear? OUTPUT: A new sheet named "Leadership Summary" for the owner, readable in two minutes: a 2-4 bullet bottom line, a small table of key numbers, at least one chart (cost per hoodie, cotton vs recycled, years 0-5), and 2-3 recommended actions, in plain English with $ and % formatting. CONTEXT: Hoodies sell for $60. Cost Projection (rows 24-29) projects cotton vs recycled cost per hoodie for 5 years (cotton fabric +4.5%/yr, recycled +1%/yr, labor +3.5%/yr). Break-even models a 25,000-click Instagram campaign: $6,300 fixed cost, $0.70/click, 4% conversion, $60 average order, $32 variable cost per order. Decisions: which fabric, and whether/how much to spend on ads. QUALITY CONTROL: Use only numbers that appear in this workbook and cite the sheet and cell for each. Do not change any cell in my existing sheets. Label every assumption (constant conversion rate, constant $5 printing, linear click-to-order model) and state limits of the model rather than guessing. If a number is not in the workbook, say so.
A19: 4. Verification log: check THREE numbers from the AI report against your own model
A20: # | B20: Number or claim in the AI report | C20: Where it lives in MY model (sheet + cell) | D20: Value in my model | E20: Match? | F20: If No: what was wrong and what did you do?
A21: e.g. | B21: A cherry bookshelf costs $513.89 in 6 years | C21: Model!E25 (class example) | D21: $513.89 | E21: Yes | F21: (example row from the class case; do not edit)
A22: 1 | B22: Cotton cost per hoodie in year 5 is $29.46 and Recycled is $28.21 (Recycled about $1.24 cheaper) | C22: Cost Projection!E29 and F29 | D22: $29.46 / $28.21 | E22: Yes | F22: n/a - matched
A23: 2 | B23: Campaign profit at 25,000 clicks is $4,200; the campaign breaks even at 15,000 clicks | C23: Break-even!E15 and E20 | D23: $4,200 / 15,000 | E23: Yes | F23: n/a - matched
A24: 3 | B24: If cost per click rises to $0.90 the campaign loses $800 | C24: Break-even!B25 (what-if answer; checked by setting B7 = 0.90, then restoring 0.70) | D24: -$800 | E24: Yes | F24: n/a - matched
A26: 5. One thing the AI got wrong, overstated, or left out, and how you knew
B27: If every number matched, name one limit of the model that the report should have mentioned to leaders.
B28: Every checked number matched, but the report should have flagged an inconsistency between the sheets: Cost Projection puts a cotton hoodie at about $25 today, while the Break-even sheet uses a flat $32 variable cost per order (hoodie + shipping + fees) for all years, so the campaign profit is not linked to the fabric decision or to rising costs. Also the break-even margin is thin: profit is only $4,200 on $60,000 of revenue, and a drop in conversion from 4% to 3.4%, or $0.90 clicks, wipes it out. I knew by comparing the two sheets' cost inputs.
A30: 6. Reflection (1 or 2 sentences): which RT-OC-QC part improved the report the most, and why?
B31: Context improved the report the most: giving the sheet names, key inputs and the two decisions let the AI answer the owner's actual questions instead of generic advice, and the Quality Control rule (cite sheet and cell, flag assumptions) made every number easy to check.

Sheet Leadership Summary
A1: Leadership Summary · Campus Threads Co.
A2: For the owner: (1) switch to recycled fabric? (2) will the Instagram campaign make money? All numbers come from the Cost Projection and Break-even sheets.
A4: Bottom line
A5: • Recycled fabric costs more per hoodie at first ($26.15 vs $25.00 today) but becomes cheaper in year 3 and is $1.24 cheaper by year 5 ($28.21 vs $29.46), because cotton and labor costs rise faster than recycled fabric (Cost Projection rows 24-29).
A6: • The planned 25,000-click Instagram campaign should make money: profit is $4,200 (Break-even!E15), with break-even at 15,000 clicks (E20).
A7: • The campaign profit is thin: it disappears if conversion falls below 3.4%, the average order falls below $55.80, or cost per click reaches $0.90 (profit becomes -$800).
A8: • The recycled savings are small (about $1.24 per hoodie by year 5, roughly 4%), so the switch is a modest cost play, not a large one.
A10: Key numbers (linked to the model)
A11: Measure | B11: Value | C11: Source
A12: Cotton cost per hoodie, year 0 | B12: ='Cost Projection'!E24 | C12: Cost Projection!E24
A13: Recycled cost per hoodie, year 0 | B13: ='Cost Projection'!F24 | C13: Cost Projection!F24
A14: Cotton cost per hoodie, year 5 | B14: ='Cost Projection'!E29 | C14: Cost Projection!E29
A15: Recycled cost per hoodie, year 5 | B15: ='Cost Projection'!F29 | C15: Cost Projection!F29
A16: Recycled premium, year 5 (negative = cheaper) | B16: ='Cost Projection'!G29 | C16: Cost Projection!G29
A17: Campaign profit at 25,000 clicks | B17: ='Break-even'!E15 | C17: Break-even!E15
A18: Break-even clicks | B18: ='Break-even'!E20 | C18: Break-even!E20
A19: Break-even conversion rate | B19: ='Break-even'!E21 | C19: Break-even!E21
A20: Break-even average order | B20: ='Break-even'!E22 | C20: Break-even!E22
A23: Charts
A44: Recommended actions
A45: 1. Run the campaign, but start near 25,000 clicks and track the conversion rate weekly; if it drops toward 3.4%, or cost per click nears $0.90, stop buying clicks.
A46: 2. Switch to recycled fabric if the sustainability appeal helps sales: it is $1.24 cheaper per hoodie by year 5 (Cost Projection!G29), but costs more for the first three years (years 0-2), so budget for the early premium.
A47: 3. Revisit the model before deciding: link the campaign's $32 variable cost to the fabric choice and test wage growth (at 6% a year a cotton hoodie costs $30.66 in year 5).
A49: Assumptions: constant 4% conversion and $60 average order; printing & trim fixed at $5; costs grow at the stated annual rates; no volume discounts, returns or repeat customers.
